buycoins/__init__.py
buycoins/client.py
buycoins/exceptions.py
buycoins/modules/__init__.py
buycoins/modules/accounts.py
buycoins/modules/orders.py
buycoins/modules/p2p.py
buycoins/modules/transactions.py
buycoins/modules/webhook.py
buycoins-1.0.2.dist-info/LICENSE
buycoins-1.0.2.dist-info/WHEEL
buycoins-1.0.2.dist-info/METADATA
buycoins-1.0.2.dist-info/RECORD
