Metadata-Version: 2.1
Name: buycoins
Version: 1.0.2
Summary: A Python SDK for the buycoins API
Home-page: https://github.com/edgeee/buycoins-python
Author: Rasheed Musa
Author-email: rasheedmusa9@gmail.com
Requires-Python: >=3.6,<3.7
Classifier: Programming Language :: Python :: 3
Classifier: Programming Language :: Python :: 3.6
Requires-Dist: gql (>=2.0.0,<3.0.0)
Project-URL: Documentation, https://github.com/edgeee/buycoins-python
Project-URL: Repository, https://github.com/edgeee/buycoins-python
